pdf2md_llm/__init__.py
pdf2md_llm/cli.py
pdf2md_llm/example_api.py
pdf2md_llm/llm.py
pdf2md_llm/pdf2img.py
pdf2md_llm/models/base_model.py
pdf2md_llm/models/qwen.py
pdf2md_llm-0.1.3.dist-info/LICENSE
pdf2md_llm-0.1.3.dist-info/METADATA
pdf2md_llm-0.1.3.dist-info/WHEEL
pdf2md_llm-0.1.3.dist-info/entry_points.txt
pdf2md_llm-0.1.3.dist-info/top_level.txt
pdf2md_llm-0.1.3.dist-info/RECORD
