Metadata-Version: 2.1
Name: pdf2md_llm
Version: 0.1.3
Summary: A package to convert PDF files to Markdown using a local LLM.
Author: Leon Eversberg
License: MIT License
Project-URL: Homepage, https://github.com/leoneversberg/pdf2md_llm
Project-URL: Repository, https://github.com/leoneversberg/pdf2md_llm.git
Keywords: markdown,pdf,llm,parser,converter
Classifier: Programming Language :: Python :: 3.10
Classifier: Programming Language :: Python :: 3.11
Classifier: License :: OSI Approved :: MIT License
Classifier: Operating System :: OS Independent
Classifier: Environment :: GPU :: NVIDIA CUDA
Classifier: Topic :: File Formats
Classifier: Topic :: Software Development :: Libraries :: Python Modules
Requires-Python: >=3.10
License-File: LICENSE
Requires-Dist: pdf2img ~=0.1.2
Requires-Dist: vllm ==0.7.3
Requires-Dist: qwen-vl-utils ~=0.0.10
Requires-Dist: accelerate ~=1.4.0
Requires-Dist: transformers ~=4.49.0
Requires-Dist: torch ==2.5.1
